edgetest_pip_tools/__init__.py
edgetest_pip_tools/plugin.py
edgetest_pip_tools-2024.8.0.dist-info/AUTHORS.md
edgetest_pip_tools-2024.8.0.dist-info/LICENSE
edgetest_pip_tools-2024.8.0.dist-info/METADATA
edgetest_pip_tools-2024.8.0.dist-info/WHEEL
edgetest_pip_tools-2024.8.0.dist-info/entry_points.txt
edgetest_pip_tools-2024.8.0.dist-info/top_level.txt
edgetest_pip_tools-2024.8.0.dist-info/RECORD
