Metadata-Version: 2.1
Name: edgetest-pip-tools
Version: 2024.8.0
Summary: pip-tools integration for edgetest
Author-email: Akshay Gupta <akshay.gupta2@capitalone.com>, Faisal Dosani <faisal.dosani@capitalone.com>, Jacob Dawang <jacob.dawang@capitalone.com>
License: Apache Software License
Project-URL: Documentation, https://capitalone.github.io/edgetest-pip-tools/
Project-URL: Bug Tracker, https://github.com/capitalone/edgetest-pip-tools/issues
Project-URL: Source Code, https://github.com/capitalone/edgetest-pip-tools
Classifier: Intended Audience :: Developers
Classifier: Natural Language :: English
Classifier: Operating System :: OS Independent
Classifier: Programming Language :: Python
Classifier: Programming Language :: Python :: 3
Classifier: Programming Language :: Python :: 3 :: Only
Classifier: Programming Language :: Python :: 3.8
Classifier: Programming Language :: Python :: 3.9
Classifier: Programming Language :: Python :: 3.10
Classifier: Programming Language :: Python :: 3.11
Requires-Python: >=3.8.0
License-File: LICENSE
License-File: AUTHORS.md
Requires-Dist: edgetest >2024.4.0
Provides-Extra: build
Requires-Dist: build ; extra == 'build'
Requires-Dist: twine ; extra == 'build'
Requires-Dist: wheel ; extra == 'build'
Requires-Dist: bumpver ; extra == 'build'
Provides-Extra: dev
Requires-Dist: edgetest-pip-tools[docs] ; extra == 'dev'
Requires-Dist: edgetest-pip-tools[tests] ; extra == 'dev'
Requires-Dist: edgetest-pip-tools[qa] ; extra == 'dev'
Requires-Dist: edgetest-pip-tools[build] ; extra == 'dev'
Provides-Extra: docs
Requires-Dist: furo ; extra == 'docs'
Requires-Dist: sphinx ; extra == 'docs'
Requires-Dist: sphinx-copybutton ; extra == 'docs'
Requires-Dist: sphinx-tabs ; extra == 'docs'
Provides-Extra: qa
Requires-Dist: mypy ; extra == 'qa'
Requires-Dist: pip-tools ; extra == 'qa'
Requires-Dist: pre-commit ; extra == 'qa'
Requires-Dist: ruff ~=0.5 ; extra == 'qa'
Requires-Dist: types-click ; extra == 'qa'
Provides-Extra: tests
Requires-Dist: coverage ; extra == 'tests'
Requires-Dist: pytest ; extra == 'tests'
Requires-Dist: pytest-cov ; extra == 'tests'
